parroter/Library/ai_artworksBot.py
parroter/Library/parroterBase.py
parroter/Library/parroterConfig.py
parroter/Library/parroterConfiger.py
parroter/Library/parroterGlobals.py
parroter/Library/ai_artworks/ai_artworksConfig.py
parroter/Library/ai_artworks/ai_artworksConfiger.py
parroter/Library/ai_artworks/ai_artworksGlobals.py
parroter/Models/trn_last_name.py
parroter-1.0.9.dist-info/METADATA
parroter-1.0.9.dist-info/WHEEL
parroter-1.0.9.dist-info/top_level.txt
parroter-1.0.9.dist-info/RECORD
